mock-stubs/METADATA.toml
mock-stubs/__init__.pyi
mock-stubs/backports.pyi
mock-stubs/mock.pyi
mock-stubs/py.typed
types_mock-5.2.0.20250809.dist-info/licenses/LICENSE
types_mock-5.2.0.20250809.dist-info/METADATA
types_mock-5.2.0.20250809.dist-info/WHEEL
types_mock-5.2.0.20250809.dist-info/top_level.txt
types_mock-5.2.0.20250809.dist-info/RECORD
